LICENSE
MANIFEST.in
setup.py
docs/index.html
docs/projectal.html
docs/projectal/api.html
docs/projectal/dynamic_enum.html
docs/projectal/dynamic_enums.html
docs/projectal/entities.html
docs/projectal/entity.html
docs/projectal/enums.html
docs/projectal/errors.html
docs/projectal/linkers.html
docs/projectal/profile.html
docs/projectal/dynamic_enums/company_types.html
docs/projectal/dynamic_enums/complexity_levels.html
docs/projectal/dynamic_enums/currency_list.html
docs/projectal/dynamic_enums/priority_levels.html
docs/projectal/dynamic_enums/skill_levels.html
docs/projectal/dynamic_enums/staff_types.html
docs/projectal/entities/access_policy.html
docs/projectal/entities/activity.html
docs/projectal/entities/booking.html
docs/projectal/entities/calendar.html
docs/projectal/entities/company.html
docs/projectal/entities/contact.html
docs/projectal/entities/customer.html
docs/projectal/entities/department.html
docs/projectal/entities/file.html
docs/projectal/entities/folder.html
docs/projectal/entities/location.html
docs/projectal/entities/note.html
docs/projectal/entities/permission.html
docs/projectal/entities/project.html
docs/projectal/entities/project_template.html
docs/projectal/entities/rebate.html
docs/projectal/entities/resource.html
docs/projectal/entities/skill.html
docs/projectal/entities/staff.html
docs/projectal/entities/stage.html
docs/projectal/entities/tag.html
docs/projectal/entities/task.html
docs/projectal/entities/task_template.html
docs/projectal/entities/user.html
docs/projectal/entities/webhook.html
examples/linking.py
examples/task.py
examples/webhook.py
projectal/__init__.py
projectal/api.py
projectal/dynamic_enum.py
projectal/entity.py
projectal/enums.py
projectal/errors.py
projectal/linkers.py
projectal/profile.py
projectal.egg-info/PKG-INFO
projectal.egg-info/SOURCES.txt
projectal.egg-info/dependency_links.txt
projectal.egg-info/requires.txt
projectal.egg-info/top_level.txt
projectal/dynamic_enums/__init__.py
projectal/dynamic_enums/company_types.py
projectal/dynamic_enums/complexity_levels.py
projectal/dynamic_enums/currency_list.py
projectal/dynamic_enums/priority_levels.py
