Metadata-Version: 2.4
Name: projectal
Version: 5.3.2
Summary: Python bindings for the Projectal API
Home-page: https://projectal.com/resources/developer
Author: Projectal
Author-email: support@projectal.com
License: MIT
Classifier: Programming Language :: Python :: 3.9
License-File: LICENSE
Requires-Dist: requests
Requires-Dist: packaging
Dynamic: author
Dynamic: author-email
Dynamic: classifier
Dynamic: description
Dynamic: description-content-type
Dynamic: home-page
Dynamic: license
Dynamic: license-file
Dynamic: requires-dist
Dynamic: summary
